setup.py
VisualizationPlotCode/__init__.py
VisualizationPlotCode/test.py
VisualizationPlotCode/visualization_code.py
VisualizationPlotCode.egg-info/PKG-INFO
VisualizationPlotCode.egg-info/SOURCES.txt
VisualizationPlotCode.egg-info/dependency_links.txt
VisualizationPlotCode.egg-info/not-zip-safe
VisualizationPlotCode.egg-info/top_level.txt