Metadata-Version: 1.0
Name: VisualizationPlotCode
Version: 1.0
Summary: plotting various figures
Home-page: https://github.com/Femi-Tofade/Visualization_Package
Author: Femi Tofade
Author-email: tolatof@gmail.com
License: UNKNOWN
Platform: UNKNOWN
